eve_sqlalchemy/__about__.py
eve_sqlalchemy/__init__.py
eve_sqlalchemy/media.py
eve_sqlalchemy/parser.py
eve_sqlalchemy/structures.py
eve_sqlalchemy/utils.py
eve_sqlalchemy/validation.py
eve_sqlalchemy/config/__init__.py
eve_sqlalchemy/config/domainconfig.py
eve_sqlalchemy/config/fieldconfig.py
eve_sqlalchemy/config/resourceconfig.py
eve_sqlalchemy/examples/__init__.py
eve_sqlalchemy/examples/auth/__init__.py
eve_sqlalchemy/examples/foreign_primary_key/__init__.py
eve_sqlalchemy/examples/foreign_primary_key/app.py
eve_sqlalchemy/examples/foreign_primary_key/domain.py
eve_sqlalchemy/examples/foreign_primary_key/settings.py
eve_sqlalchemy/examples/many_to_many/__init__.py
eve_sqlalchemy/examples/many_to_many/app.py
eve_sqlalchemy/examples/many_to_many/domain.py
eve_sqlalchemy/examples/many_to_many/settings.py
eve_sqlalchemy/examples/many_to_one/__init__.py
eve_sqlalchemy/examples/many_to_one/app.py
eve_sqlalchemy/examples/many_to_one/domain.py
eve_sqlalchemy/examples/many_to_one/settings.py
eve_sqlalchemy/examples/multiple_dbs/__init__.py
eve_sqlalchemy/examples/multiple_dbs/app.py
eve_sqlalchemy/examples/multiple_dbs/domain.py
eve_sqlalchemy/examples/multiple_dbs/settings.py
eve_sqlalchemy/examples/one_to_many/__init__.py
eve_sqlalchemy/examples/one_to_many/app.py
eve_sqlalchemy/examples/one_to_many/domain.py
eve_sqlalchemy/examples/one_to_many/settings.py
eve_sqlalchemy/examples/simple/__init__.py
eve_sqlalchemy/examples/simple/app.py
eve_sqlalchemy/examples/simple/example_data.py
eve_sqlalchemy/examples/simple/settings.py
eve_sqlalchemy/examples/simple/tables.py
eve_sqlalchemy/examples/trivial/__init__.py
eve_sqlalchemy/examples/trivial/trivial.py
eve_sqlalchemy/tests/__init__.py
eve_sqlalchemy/tests/delete.py
eve_sqlalchemy/tests/get.py
eve_sqlalchemy/tests/patch.py
eve_sqlalchemy/tests/post.py
eve_sqlalchemy/tests/put.py
eve_sqlalchemy/tests/sql.py
eve_sqlalchemy/tests/test_settings.py
eve_sqlalchemy/tests/test_sql_tables.py
eve_sqlalchemy_3.10-0.7.2.dev0.dist-info/AUTHORS
eve_sqlalchemy_3.10-0.7.2.dev0.dist-info/LICENSE
eve_sqlalchemy_3.10-0.7.2.dev0.dist-info/METADATA
eve_sqlalchemy_3.10-0.7.2.dev0.dist-info/WHEEL
eve_sqlalchemy_3.10-0.7.2.dev0.dist-info/top_level.txt
eve_sqlalchemy_3.10-0.7.2.dev0.dist-info/zip-safe
eve_sqlalchemy_3.10-0.7.2.dev0.dist-info/RECORD
