Metadata-Version: 2.1
Name: eve-sqlalchemy-3.10
Version: 0.7.2.dev0
Summary: REST API framework powered by Eve, SQLAlchemy and good intentions.
Home-page: https://github.com/pyeve/eve-sqlalchemy
Author: Dominik Kellner
Author-email: dkellner@dkellner.de
License: BSD
Keywords: flask sqlalchemy rest
Platform: any
Classifier: Development Status :: 4 - Beta
Classifier: Environment :: Web Environment
Classifier: Intended Audience :: Developers
Classifier: License :: OSI Approved :: BSD License
Classifier: Operating System :: OS Independent
Classifier: Programming Language :: Python
Classifier: Programming Language :: Python :: 2
Classifier: Programming Language :: Python :: 2.7
Classifier: Programming Language :: Python :: 3
Classifier: Programming Language :: Python :: 3.4
Classifier: Programming Language :: Python :: 3.5
Classifier: Programming Language :: Python :: 3.6
Classifier: Programming Language :: Python :: 3.7
Classifier: Programming Language :: Python :: Implementation :: CPython
Classifier: Programming Language :: Python :: Implementation :: PyPy
Classifier: Topic :: Internet :: WWW/HTTP :: Dynamic Content
License-File: LICENSE
License-File: AUTHORS
Requires-Dist: Eve (~=2.0.4)
Requires-Dist: Flask-SQLAlchemy (~=2.5.1)
Requires-Dist: SQLAlchemy (>=1.4.44)
Requires-Dist: flask (~=2.1.3)
Provides-Extra: test
Requires-Dist: mock ; extra == 'test'
Requires-Dist: pytest ; extra == 'test'
